dl_wp_pdf.py
dl_wp_pdf-0.10.dist-info/METADATA
dl_wp_pdf-0.10.dist-info/WHEEL
dl_wp_pdf-0.10.dist-info/entry_points.txt
dl_wp_pdf-0.10.dist-info/licenses/LICENSE
dl_wp_pdf-0.10.dist-info/RECORD
