Metadata-Version: 2.3
Name: dl-wp-pdf
Version: 0.10
Summary: Download Wikipedia articles as PDF
Project-URL: Homepage, https://codeberg.org/hyperreal/dl-wp-pdf
Project-URL: Issues, https://codeberg.org/hyperreal/dl-wp-pdf/issues
Author-email: Jeffrey Serio <hyperreal@fedoraproject.org>
Classifier: License :: OSI Approved :: GNU General Public License v3 or later (GPLv3+)
Classifier: Operating System :: OS Independent
Classifier: Programming Language :: Python :: 3
Requires-Python: >=3.10
